godot_parser/__init__.py
godot_parser/files.py
godot_parser/objects.py
godot_parser/py.typed
godot_parser/sections.py
godot_parser/structure.py
godot_parser/tree.py
godot_parser/util.py
godot_parser/values.py
godot_parser-0.1.7.dist-info/LICENSE
godot_parser-0.1.7.dist-info/METADATA
godot_parser-0.1.7.dist-info/WHEEL
godot_parser-0.1.7.dist-info/top_level.txt
godot_parser-0.1.7.dist-info/RECORD
