Metadata-Version: 2.1
Name: godot-parser
Version: 0.1.7
Summary: Python library for parsing Godot scene files
Home-page: https://github.com/stevearc/godot_parser
Author: Steven Arcangeli
Author-email: stevearc@stevearc.com
License: MIT
Keywords: godot parse parser scene
Platform: any
Classifier: Programming Language :: Python
Classifier: Programming Language :: Python :: 3
Classifier: Programming Language :: Python :: 3.7
Classifier: Programming Language :: Python :: 3.8
Classifier: Programming Language :: Python :: 3.9
Classifier: Programming Language :: Python :: 3.10
Classifier: Programming Language :: Python :: 3.11
Classifier: Development Status :: 3 - Alpha
Classifier: Intended Audience :: Developers
Classifier: License :: OSI Approved :: MIT License
Requires-Python: >=3.6
License-File: LICENSE
Requires-Dist: pyparsing >=3
